spec2epsilon/__init__.py
spec2epsilon/__main__.py
spec2epsilon/__version__.py
spec2epsilon/api.py
spec2epsilon/app.py
spec2epsilon/load-mathjax.js
spec2epsilon/visualization.py
spec2epsilon-0.0.2.dist-info/licenses/LICENSE
spec2epsilon-0.0.2.dist-info/METADATA
spec2epsilon-0.0.2.dist-info/WHEEL
spec2epsilon-0.0.2.dist-info/entry_points.txt
spec2epsilon-0.0.2.dist-info/top_level.txt
spec2epsilon-0.0.2.dist-info/RECORD
