Metadata-Version: 2.4
Name: spec2epsilon
Version: 0.0.2
Summary: Estimate dielectric constant from fluorescence spectra
Author-email: Leonardo Evaristo de Sousa <ledso@dtu.dk>
License-Expression: MIT
Project-URL: Homepage, https://github.com/LeonardoESousa/spec2epsilon
Requires-Python: >=3.8
License-File: LICENSE
Requires-Dist: numpy<2.0,>=1.23
Requires-Dist: pandas<2.0,>=1.5
Requires-Dist: scipy
Requires-Dist: streamlit[charts]
Dynamic: license-file
